[
  {
    "City": "Melbourne",
    "Certificate": 15,
    "Graduate Degree": 4.7,
    "Bachelor Degree": 16.6,
    "Rate of Mentioning COVID": 0.573613767
  },
  {
    "City": "Brisbane",
    "Certificate": 18.1,
    "Graduate Degree": 3.9,
    "Bachelor Degree": 14.5,
    "Rate of Mentioning COVID": 0.519390582
  },
  {
    "City": "Adelaide",
    "Certificate": 18.1,
    "Graduate Degree": 3.3,
    "Bachelor Degree": 13.2,
    "Rate of Mentioning COVID": 0.402468473
  },
  {
    "City": "Perth",
    "Certificate": 18.6,
    "Graduate Degree": 3.4,
    "Bachelor Degree": 14.5,
    "Rate of Mentioning COVID": 0.773623135
  },
  {
    "City": "Sydney",
    "Certificate": 15.2,
    "Graduate Degree": 5.6,
    "Bachelor Degree": 16.9,
    "Rate of Mentioning COVID": 0.715049206
  }
]